{"@context": "https://schema.org/", "@type": "Dataset", "name": "日本の都道府県（2010年4月）", "keywords": ["GeoNLP", "地名辞書"], "alternateName": "", "description": "1都1道2府43県の辞書です。県庁所在地の住所を含みます。自由フィールドとして県庁の代表電話番号も含みます。代表点の座標は県庁の住所をジオコーディングにより取得しています。", "url": "https://geonlp.ex.nii.ac.jp/dictionary/geoshape-pref/", "distribution": [{"@type": "DataDownload", "contentUrl": "http://agora.ex.nii.ac.jp/GeoNLP/dict/geoshape-pref.csv", "encodingFormat": "text/csv"}], "identifier": ["geonlp:geoshape-pref"], "dateModified": "2014-01-15T14:36:17+09:00", "license": "https://creativecommons.org/licenses/by/4.0/", "size": "48", "temporalCoverage": "../..", "creator": [{"name": "GeoNLP Project", "@type": "Organization", "sameAs": "http://geonlp.ex.nii.ac.jp/"}], "isBasedOn": {"@type": "CreativeWork", "name": "財団法人地方自治情報センター「都道府県庁」", "url": "https://www.lasdec.or.jp/cms/1,69,14,188,html"}, "spatialCoverage": {"@type": "Place", "geo": {"@type": "GeoShape", "box": "26.2133 126.67963 43.06411 141.34702"}}}
